depthcharge_tools/__init__.py
depthcharge_tools/boards.ini
depthcharge_tools/config.ini
depthcharge_tools/mkdepthcharge.py
depthcharge_tools/depthchargectl/__init__.py
depthcharge_tools/depthchargectl/__main__.py
depthcharge_tools/depthchargectl/_bless.py
depthcharge_tools/depthchargectl/_build.py
depthcharge_tools/depthchargectl/_check.py
depthcharge_tools/depthchargectl/_config.py
depthcharge_tools/depthchargectl/_list.py
depthcharge_tools/depthchargectl/_remove.py
depthcharge_tools/depthchargectl/_target.py
depthcharge_tools/depthchargectl/_write.py
depthcharge_tools/utils/__init__.py
depthcharge_tools/utils/argparse.py
depthcharge_tools/utils/collections.py
depthcharge_tools/utils/os.py
depthcharge_tools/utils/pathlib.py
depthcharge_tools/utils/platform.py
depthcharge_tools/utils/string.py
depthcharge_tools/utils/subprocess.py
depthcharge_tools-0.6.2.dist-info/COPYRIGHT
depthcharge_tools-0.6.2.dist-info/LICENSE
depthcharge_tools-0.6.2.dist-info/METADATA
depthcharge_tools-0.6.2.dist-info/WHEEL
depthcharge_tools-0.6.2.dist-info/entry_points.txt
depthcharge_tools-0.6.2.dist-info/top_level.txt
depthcharge_tools-0.6.2.dist-info/RECORD
