Metadata-Version: 2.1
Name: depthcharge-tools
Version: 0.6.2
Summary: Tools to manage the Chrome OS bootloader
Home-page: https://github.com/alpernebbi/depthcharge-tools
Author: Alper Nebi Yasak
Author-email: alpernebiyasak@gmail.com
License: GPL2+
Keywords: ChromeOS ChromiumOS depthcharge vboot vbutil_kernel
Classifier: Development Status :: 3 - Alpha
Classifier: Environment :: Console
Classifier: Intended Audience :: Developers
Classifier: License :: OSI Approved :: GNU General Public License v2 or later (GPLv2+)
Classifier: Operating System :: POSIX :: Linux
Classifier: Programming Language :: Python :: 3
Classifier: Topic :: System :: Boot
License-File: LICENSE
License-File: COPYRIGHT
Requires-Dist: setuptools
